sk_stepwise/__init__.py
sk_stepwise-0.1.2.dist-info/METADATA
sk_stepwise-0.1.2.dist-info/WHEEL
sk_stepwise-0.1.2.dist-info/top_level.txt
sk_stepwise-0.1.2.dist-info/RECORD
