Metadata-Version: 2.4
Name: sk-stepwise
Version: 0.1.2
Summary: Add your description here
Requires-Python: >=3.11
Requires-Dist: disutils>=1.4.32.post2
Requires-Dist: hyperopt>=0.2.7
Requires-Dist: numpy>=2.1.1
Requires-Dist: pandas>=2.2.2
Requires-Dist: scikit-learn>=1.5.2
Requires-Dist: setuptools>=75.1.0
Requires-Dist: xgboost>=2.1.1
